countess_variants/__init__.py
countess_variants/caller.py
countess_variants/py.typed
countess_variants-0.0.1.dist-info/METADATA
countess_variants-0.0.1.dist-info/WHEEL
countess_variants-0.0.1.dist-info/entry_points.txt
countess_variants-0.0.1.dist-info/top_level.txt
countess_variants-0.0.1.dist-info/RECORD
