Metadata-Version: 2.1
Name: countess-variants
Version: 0.0.1
Summary: CountESS Variant Calling Plugin
Author-email: Nick Moore <nick@zoic.org>
Maintainer-email: Nick Moore <nick@zoic.org>
License: BSD-3-Clause
Classifier: Development Status :: 2 - Pre-Alpha
Classifier: Intended Audience :: Science/Research
Classifier: License :: OSI Approved :: BSD License
Classifier: Operating System :: OS Independent
Classifier: Topic :: Scientific/Engineering :: Bio-Informatics
Requires-Python: >=3.10
Requires-Dist: countess (<0.1,>=0.0.31)
Requires-Dist: sequence-align (==0.1.0)
Provides-Extra: dev
Requires-Dist: countess[dev] (<0.1,>=0.0.31) ; extra == 'dev'
